setup.py
distributions_aws_ml/Binomialdistribution.py
distributions_aws_ml/Gaussiandistribution.py
distributions_aws_ml/Generaldistribution.py
distributions_aws_ml/__init__.py
distributions_aws_ml.egg-info/PKG-INFO
distributions_aws_ml.egg-info/SOURCES.txt
distributions_aws_ml.egg-info/dependency_links.txt
distributions_aws_ml.egg-info/not-zip-safe
distributions_aws_ml.egg-info/top_level.txt